ShuxueZhimeiLangchaoZhidianGugeHeibanbao/README.md
ShuxueZhimeiLangchaoZhidianGugeHeibanbao/__init__.py
ShuxueZhimeiLangchaoZhidianGugeHeibanbao/__main__.py
ShuxueZhimeiLangchaoZhidianGugeHeibanbao/file.epub
ShuxueZhimeiLangchaoZhidianGugeHeibanbao/index.html
ShuxueZhimeiLangchaoZhidianGugeHeibanbao/css/__init__.py
ShuxueZhimeiLangchaoZhidianGugeHeibanbao/css/annotations.css
ShuxueZhimeiLangchaoZhidianGugeHeibanbao/css/main.css
ShuxueZhimeiLangchaoZhidianGugeHeibanbao/css/normalize.css
ShuxueZhimeiLangchaoZhidianGugeHeibanbao/css/popup.css
ShuxueZhimeiLangchaoZhidianGugeHeibanbao/font/__init__.py
ShuxueZhimeiLangchaoZhidianGugeHeibanbao/font/fontello.eot
ShuxueZhimeiLangchaoZhidianGugeHeibanbao/font/fontello.svg
ShuxueZhimeiLangchaoZhidianGugeHeibanbao/font/fontello.ttf
ShuxueZhimeiLangchaoZhidianGugeHeibanbao/font/fontello.woff
ShuxueZhimeiLangchaoZhidianGugeHeibanbao/img/__init__.py
ShuxueZhimeiLangchaoZhidianGugeHeibanbao/img/annotator-glyph-sprite.png
ShuxueZhimeiLangchaoZhidianGugeHeibanbao/img/annotator-icon-sprite.png
ShuxueZhimeiLangchaoZhidianGugeHeibanbao/img/apple-touch-icon.png
ShuxueZhimeiLangchaoZhidianGugeHeibanbao/img/cancelfullscreen.png
ShuxueZhimeiLangchaoZhidianGugeHeibanbao/img/close.png
ShuxueZhimeiLangchaoZhidianGugeHeibanbao/img/fullscreen.png
ShuxueZhimeiLangchaoZhidianGugeHeibanbao/img/loader.gif
ShuxueZhimeiLangchaoZhidianGugeHeibanbao/img/menu-icon.png
ShuxueZhimeiLangchaoZhidianGugeHeibanbao/img/save.png
ShuxueZhimeiLangchaoZhidianGugeHeibanbao/img/saved.png
ShuxueZhimeiLangchaoZhidianGugeHeibanbao/img/settings-s.png
ShuxueZhimeiLangchaoZhidianGugeHeibanbao/img/settings.png
ShuxueZhimeiLangchaoZhidianGugeHeibanbao/img/star.png
ShuxueZhimeiLangchaoZhidianGugeHeibanbao/js/__init__.py
ShuxueZhimeiLangchaoZhidianGugeHeibanbao/js/epub.js
ShuxueZhimeiLangchaoZhidianGugeHeibanbao/js/epub.min.js
ShuxueZhimeiLangchaoZhidianGugeHeibanbao/js/epub.min.map
ShuxueZhimeiLangchaoZhidianGugeHeibanbao/js/hooks.min.js
shuxue_zhimei_langchao_zhidian_guge_heibanbao-2024.3.2.0.dist-info/METADATA
shuxue_zhimei_langchao_zhidian_guge_heibanbao-2024.3.2.0.dist-info/WHEEL
shuxue_zhimei_langchao_zhidian_guge_heibanbao-2024.3.2.0.dist-info/entry_points.txt
shuxue_zhimei_langchao_zhidian_guge_heibanbao-2024.3.2.0.dist-info/top_level.txt
shuxue_zhimei_langchao_zhidian_guge_heibanbao-2024.3.2.0.dist-info/RECORD
